pumpswapamm/__init__.py
pumpswapamm/fetch_reserves.py
pumpswapamm/pumpswapamm.py
pumpswapamm-2.2.dist-info/METADATA
pumpswapamm-2.2.dist-info/WHEEL
pumpswapamm-2.2.dist-info/top_level.txt
pumpswapamm-2.2.dist-info/RECORD
