Metadata-Version: 2.1
Name: pumpswapamm
Version: 2.2
Summary: Python SDK for Pump.fun’s PumpSwap AMM on Solana
Author: FLOCK4H
License: MIT
Classifier: Programming Language :: Python :: 3
Classifier: License :: OSI Approved :: MIT License
Classifier: Operating System :: OS Independent
Requires-Python: >=3.10
Requires-Dist: solana==0.35.1
Requires-Dist: solders==0.21.0
Requires-Dist: construct
Requires-Dist: base58
